{
  "Jockey_MarkingDistanceSecondaryPress": {
    "External": {
      "FileGuid": "00000000-0000-0000-0000-000000000000",
      "ClassGuid": "00000000-0000-0000-0000-000000000000"
    },
    "Internal": {
      "Points": [
        {
          "CurveType": 2,
          "X": 0.0,
          "OutTangentOffsetY": 0.0,
          "InTangentOffsetY": 0.0,
          "Y": 6.0,
          "InTangentOffsetX": -1.0,
          "OutTangentOffsetX": 1.0
        },
        {
          "CurveType": 2,
          "X": 20.0,
          "OutTangentOffsetY": 0.0,
          "InTangentOffsetY": 0.0,
          "Y": 6.0,
          "InTangentOffsetX": -1.0,
          "OutTangentOffsetX": 1.0
        },
        {
          "CurveType": 2,
          "X": 53.75,
          "OutTangentOffsetY": 0.0,
          "InTangentOffsetY": 0.0,
          "Y": 10.0,
          "InTangentOffsetX": -1.0,
          "OutTangentOffsetX": 1.0
        },
        {
          "CurveType": 2,
          "X": 172.0,
          "OutTangentOffsetY": 0.0,
          "InTangentOffsetY": 0.0,
          "Y": 16.0,
          "InTangentOffsetX": -1.0,
          "OutTangentOffsetX": 1.0
        }
      ],
      "MaxX": 344.0,
      "MinX": 0.0,
      "__InstanceGuid": {
        "ExportedGuid": "fdc1eca2-4392-3add-d94a-b2f175dbc1ad",
        "InternalId": 6,
        "IsExported": true
      }
    },
    "Type": 1
  },
  "Jockey_MarkingDistanceShielded": {
    "External": {
      "FileGuid": "00000000-0000-0000-0000-000000000000",
      "ClassGuid": "00000000-0000-0000-0000-000000000000"
    },
    "Internal": {
      "Points": [
        {
          "CurveType": 2,
          "X": 0.0,
          "OutTangentOffsetY": 0.0,
          "InTangentOffsetY": 0.0,
          "Y": 6.0,
          "InTangentOffsetX": -1.0,
          "OutTangentOffsetX": 1.0
        },
        {
          "CurveType": 2,
          "X": 20.0,
          "OutTangentOffsetY": 0.0,
          "InTangentOffsetY": 0.0,
          "Y": 6.0,
          "InTangentOffsetX": -1.0,
          "OutTangentOffsetX": 1.0
        },
        {
          "CurveType": 2,
          "X": 53.75,
          "OutTangentOffsetY": 0.0,
          "InTangentOffsetY": 0.0,
          "Y": 10.0,
          "InTangentOffsetX": -1.0,
          "OutTangentOffsetX": 1.0
        },
        {
          "CurveType": 2,
          "X": 172.0,
          "OutTangentOffsetY": 0.0,
          "InTangentOffsetY": 0.0,
          "Y": 16.0,
          "InTangentOffsetX": -1.0,
          "OutTangentOffsetX": 1.0
        }
      ],
      "MaxX": 344.0,
      "MinX": 0.0,
      "__InstanceGuid": {
        "ExportedGuid": "33a056d2-a778-7590-9670-41233366f050",
        "InternalId": 8,
        "IsExported": true
      }
    },
    "Type": 1
  },
  "Jockey_MarkingDistance": {
    "External": {
      "FileGuid": "00000000-0000-0000-0000-000000000000",
      "ClassGuid": "00000000-0000-0000-0000-000000000000"
    },
    "Internal": {
      "Points": [
        {
          "CurveType": 2,
          "X": 0.0,
          "OutTangentOffsetY": 0.0,
          "InTangentOffsetY": 0.0,
          "Y": 6.0,
          "InTangentOffsetX": -1.0,
          "OutTangentOffsetX": 1.0
        },
        {
          "CurveType": 2,
          "X": 20.0,
          "OutTangentOffsetY": 0.0,
          "InTangentOffsetY": 0.0,
          "Y": 6.0,
          "InTangentOffsetX": -1.0,
          "OutTangentOffsetX": 1.0
        },
        {
          "CurveType": 2,
          "X": 53.75,
          "OutTangentOffsetY": 0.0,
          "InTangentOffsetY": 0.0,
          "Y": 10.0,
          "InTangentOffsetX": -1.0,
          "OutTangentOffsetX": 1.0
        },
        {
          "CurveType": 2,
          "X": 172.0,
          "OutTangentOffsetY": 0.0,
          "InTangentOffsetY": 0.0,
          "Y": 16.0,
          "InTangentOffsetX": -1.0,
          "OutTangentOffsetX": 1.0
        }
      ],
      "MaxX": 344.0,
      "MinX": 0.0,
      "__InstanceGuid": {
        "ExportedGuid": "deaf8e07-cbe5-2839-52c1-ec63dcd78e5f",
        "InternalId": 1,
        "IsExported": true
      }
    },
    "Type": 1
  },
  "Jockey_ReactionTimeModifier": {
    "External": {
      "FileGuid": "00000000-0000-0000-0000-000000000000",
      "ClassGuid": "00000000-0000-0000-0000-000000000000"
    },
    "Internal": {
      "Points": [
        {
          "CurveType": 2,
          "X": 0.0,
          "OutTangentOffsetY": 0.0,
          "InTangentOffsetY": 0.0,
          "Y": 1.3,
          "InTangentOffsetX": -1.0,
          "OutTangentOffsetX": 1.0
        },
        {
          "CurveType": 2,
          "X": 0.2,
          "OutTangentOffsetY": 0.0,
          "InTangentOffsetY": 0.0,
          "Y": 1.4,
          "InTangentOffsetX": -1.0,
          "OutTangentOffsetX": 1.0
        },
        {
          "CurveType": 2,
          "X": 0.4,
          "OutTangentOffsetY": 0.0,
          "InTangentOffsetY": 0.0,
          "Y": 1.45,
          "InTangentOffsetX": -1.0,
          "OutTangentOffsetX": 1.0
        },
        {
          "CurveType": 2,
          "X": 0.6,
          "OutTangentOffsetY": 0.0,
          "InTangentOffsetY": 0.0,
          "Y": 1.5,
          "InTangentOffsetX": -1.0,
          "OutTangentOffsetX": 1.0
        },
        {
          "CurveType": 2,
          "X": 0.8,
          "OutTangentOffsetY": 0.0,
          "InTangentOffsetY": 0.0,
          "Y": 1.6,
          "InTangentOffsetX": -1.0,
          "OutTangentOffsetX": 1.0
        },
        {
          "CurveType": 2,
          "X": 1.0,
          "OutTangentOffsetY": 0.0,
          "InTangentOffsetY": 0.0,
          "Y": 1.7,
          "InTangentOffsetX": -1.0,
          "OutTangentOffsetX": 1.0
        }
      ],
      "MaxX": 1.0,
      "MinX": 0.0,
      "__InstanceGuid": {
        "ExportedGuid": "e9879260-cb3c-55d6-6a8a-5e6f0d77d774",
        "InternalId": 4,
        "IsExported": true
      }
    },
    "Type": 1
  },
  "Jockey_ReactionTime": {
    "External": {
      "FileGuid": "00000000-0000-0000-0000-000000000000",
      "ClassGuid": "00000000-0000-0000-0000-000000000000"
    },
    "Internal": {
      "Points": [
        {
          "CurveType": 2,
          "X": 0.0,
          "OutTangentOffsetY": 0.0,
          "InTangentOffsetY": 0.0,
          "Y": 11.0,
          "InTangentOffsetX": -1.0,
          "OutTangentOffsetX": 1.0
        },
        {
          "CurveType": 2,
          "X": 0.5,
          "OutTangentOffsetY": 0.0,
          "InTangentOffsetY": 0.0,
          "Y": 11.0,
          "InTangentOffsetX": -1.0,
          "OutTangentOffsetX": 1.0
        },
        {
          "CurveType": 2,
          "X": 0.6,
          "OutTangentOffsetY": 0.0,
          "InTangentOffsetY": 0.0,
          "Y": 10.85,
          "InTangentOffsetX": -1.0,
          "OutTangentOffsetX": 1.0
        },
        {
          "CurveType": 2,
          "X": 0.7,
          "OutTangentOffsetY": 0.0,
          "InTangentOffsetY": 0.0,
          "Y": 10.5,
          "InTangentOffsetX": -1.0,
          "OutTangentOffsetX": 1.0
        },
        {
          "CurveType": 2,
          "X": 0.8,
          "OutTangentOffsetY": 0.0,
          "InTangentOffsetY": 0.0,
          "Y": 10.0,
          "InTangentOffsetX": -1.0,
          "OutTangentOffsetX": 1.0
        },
        {
          "CurveType": 2,
          "X": 0.9,
          "OutTangentOffsetY": 0.0,
          "InTangentOffsetY": 0.0,
          "Y": 9.25,
          "InTangentOffsetX": -1.0,
          "OutTangentOffsetX": 1.0
        },
        {
          "CurveType": 2,
          "X": 1.0,
          "OutTangentOffsetY": 0.0,
          "InTangentOffsetY": 0.0,
          "Y": 8.0,
          "InTangentOffsetX": -1.0,
          "OutTangentOffsetX": 1.0
        }
      ],
      "MaxX": 1.0,
      "MinX": 0.0,
      "__InstanceGuid": {
        "ExportedGuid": "5d56f422-bed5-424a-cfed-2fd4f340ea00",
        "InternalId": 2,
        "IsExported": true
      }
    },
    "Type": 1
  },
  "Jockey_PadEffectJockeyModifyAngle": {
    "External": {
      "FileGuid": "00000000-0000-0000-0000-000000000000",
      "ClassGuid": "00000000-0000-0000-0000-000000000000"
    },
    "Internal": {
      "Points": [
        {
          "CurveType": 2,
          "X": 0.0,
          "OutTangentOffsetY": 0.0,
          "InTangentOffsetY": 0.0,
          "Y": 0.0,
          "InTangentOffsetX": -1.0,
          "OutTangentOffsetX": 1.0
        },
        {
          "CurveType": 2,
          "X": 0.5,
          "OutTangentOffsetY": 0.0,
          "InTangentOffsetY": 0.0,
          "Y": 18.752,
          "InTangentOffsetX": -1.0,
          "OutTangentOffsetX": 1.0
        },
        {
          "CurveType": 2,
          "X": 1.0,
          "OutTangentOffsetY": 0.0,
          "InTangentOffsetY": 0.0,
          "Y": 0.0,
          "InTangentOffsetX": -1.0,
          "OutTangentOffsetX": 1.0
        }
      ],
      "MaxX": 1.0,
      "MinX": 0.0,
      "__InstanceGuid": {
        "ExportedGuid": "fd3c8132-ae09-378e-5e53-f799cf5092ad",
        "InternalId": 3,
        "IsExported": true
      }
    },
    "Type": 1
  },
  "Jockey_PadEffectJockeyShieldedModifyAngle": {
    "External": {
      "FileGuid": "00000000-0000-0000-0000-000000000000",
      "ClassGuid": "00000000-0000-0000-0000-000000000000"
    },
    "Internal": {
      "Points": [
        {
          "CurveType": 2,
          "X": 0.0,
          "OutTangentOffsetY": 0.0,
          "InTangentOffsetY": 0.0,
          "Y": 0.0,
          "InTangentOffsetX": -1.0,
          "OutTangentOffsetX": 1.0
        },
        {
          "CurveType": 2,
          "X": 0.5,
          "OutTangentOffsetY": 0.0,
          "InTangentOffsetY": 0.0,
          "Y": 18.752,
          "InTangentOffsetX": -1.0,
          "OutTangentOffsetX": 1.0
        },
        {
          "CurveType": 2,
          "X": 1.0,
          "OutTangentOffsetY": 0.0,
          "InTangentOffsetY": 0.0,
          "Y": 0.0,
          "InTangentOffsetX": -1.0,
          "OutTangentOffsetX": 1.0
        }
      ],
      "MaxX": 1.0,
      "MinX": 0.0,
      "__InstanceGuid": {
        "ExportedGuid": "155eed60-2a0a-ded5-2db5-1c79bdeed57e",
        "InternalId": 5,
        "IsExported": true
      }
    },
    "Type": 1
  },
  "Jockey_PadEffectJockeyModifyDistance": {
    "External": {
      "FileGuid": "00000000-0000-0000-0000-000000000000",
      "ClassGuid": "00000000-0000-0000-0000-000000000000"
    },
    "Internal": {
      "Points": [
        {
          "CurveType": 2,
          "X": 0.0,
          "OutTangentOffsetY": 0.0,
          "InTangentOffsetY": 0.0,
          "Y": 0.0,
          "InTangentOffsetX": -1.0,
          "OutTangentOffsetX": 1.0
        },
        {
          "CurveType": 2,
          "X": 1.0,
          "OutTangentOffsetY": 0.0,
          "InTangentOffsetY": 0.0,
          "Y": 6.0,
          "InTangentOffsetX": -1.0,
          "OutTangentOffsetX": 1.0
        }
      ],
      "MaxX": 1.0,
      "MinX": 0.0,
      "__InstanceGuid": {
        "ExportedGuid": "9d5133aa-7df2-0e8b-e442-009830deab82",
        "InternalId": 7,
        "IsExported": true
      }
    },
    "Type": 1
  },
  "Jockey_PadEffectJockeyShieldedModifyDistance": {
    "External": {
      "FileGuid": "00000000-0000-0000-0000-000000000000",
      "ClassGuid": "00000000-0000-0000-0000-000000000000"
    },
    "Internal": {
      "Points": [
        {
          "CurveType": 2,
          "X": 0.0,
          "OutTangentOffsetY": 0.0,
          "InTangentOffsetY": 0.0,
          "Y": 0.0,
          "InTangentOffsetX": -1.0,
          "OutTangentOffsetX": 1.0
        },
        {
          "CurveType": 2,
          "X": 1.0,
          "OutTangentOffsetY": 0.0,
          "InTangentOffsetY": 0.0,
          "Y": 6.0,
          "InTangentOffsetX": -1.0,
          "OutTangentOffsetX": 1.0
        }
      ],
      "MaxX": 1.0,
      "MinX": 0.0,
      "__InstanceGuid": {
        "ExportedGuid": "4ca12ee4-68c4-6848-2dfd-2da63d9dff5f",
        "InternalId": 9,
        "IsExported": true
      }
    },
    "Type": 1
  },
  "MinSprintSpeed": 0.28,
  "FastJockey_zDistanceThreshold": 9.0,
  "FastJockey_BallLookAheadTime": 12.0,
  "MaxSprintSpeed": 0.35,
  "SprintSpeed_MinMarkingAttr": 0.6,
  "FastJockey_ClampFaceToMove": 45.0,
  "FastJockey_TogglingThreshold": 176.0,
  "FastJockey_FuturePlayerTime": 30.0,
  "FastJockey_ClampFaceToBall": 90.0,
  "SprintSpeed_MaxMarkingAttr": 0.99,
  "BaseField": 0,
  "Name": {
    "StrValue": "Fifa/Attribulator/Gameplay/groups/gp_defense/gp_defense_jockey_runtime"
  },
  "__InstanceGuid": {
    "ExportedGuid": "7dcdcbe6-14cc-ec03-209f-6bac082f1b4b",
    "InternalId": 0,
    "IsExported": true
  }
}